{
  "done": true,
  "migration": {
    "name": "mig_cts2chk1dm7utqqg0fn0",
    "operations": [
      {
        "add_column": {
          "table": "products",
          "column": {
            "name": "sku",
            "type": "text",
            "comment": "",
            "nullable": true
          }
        }
      }
    ]
  },
  "migrationType": "pgroll",
  "name": "mig_cts2chk1dm7utqqg0fn0",
  "parent": "mig_cts2cebnjla46jgojv7g",
  "schema": "public",
  "startedAt": "2025-01-03T18:02:47.68825Z"
}
